kiss_ai_stack_types/__init__.py
kiss_ai_stack_types/enums/__init__.py
kiss_ai_stack_types/enums/events.py
kiss_ai_stack_types/enums/server_event_action.py
kiss_ai_stack_types/enums/session_scope.py
kiss_ai_stack_types/models/__init__.py
kiss_ai_stack_types/models/auth.py
kiss_ai_stack_types/models/documents.py
kiss_ai_stack_types/models/queries.py
kiss_ai_stack_types/models/responses.py
kiss_ai_stack_types-0.1.0a4.dist-info/LICENSE
kiss_ai_stack_types-0.1.0a4.dist-info/METADATA
kiss_ai_stack_types-0.1.0a4.dist-info/WHEEL
kiss_ai_stack_types-0.1.0a4.dist-info/top_level.txt
kiss_ai_stack_types-0.1.0a4.dist-info/RECORD
