Metadata-Version: 2.1
Name: kiss-ai-stack-types
Version: 0.1.0a4
Summary: KISS AI Stack's common object types
Author: KISS AI Stack, Lahiru Pathirage
License: MIT
Project-URL: Homepage, https://github.com/kiss-ai-stack
Project-URL: Repository, https://github.com/kiss-ai-stack
Project-URL: Documentation, https://github.com/kiss-ai-stack/kiss-ai-stack-types/main/README.md
Keywords: ai,agent,machine-learning,llm,document-processing
Classifier: Development Status :: 3 - Alpha
Classifier: Intended Audience :: Developers
Classifier: License :: OSI Approved :: MIT License
Classifier: Programming Language :: Python :: 3.12
Classifier: Topic :: Scientific/Engineering :: Artificial Intelligence
Requires-Python: >=3.12
License-File: LICENSE
Requires-Dist: pydantic~=2.10.3
